preprocess_kgptalkie/__init__.py
preprocess_kgptalkie/text_preprocess.py
preprocess_kgptalkie/data/contractions.json
preprocess_kgptalkie-0.11.dist-info/LICENSE
preprocess_kgptalkie-0.11.dist-info/METADATA
preprocess_kgptalkie-0.11.dist-info/WHEEL
preprocess_kgptalkie-0.11.dist-info/top_level.txt
preprocess_kgptalkie-0.11.dist-info/RECORD
