Metadata-Version: 2.1
Name: preprocess_kgptalkie
Version: 0.11
Summary: This is a text preprocessing package
Author: Laxmi Kant
Author-email: udemy@kgptalkie.com
Classifier: Programming Language :: Python :: 3
Classifier: License :: OSI Approved :: MIT License
Classifier: Operating System :: OS Independent
Requires-Python: >=3.7
License-File: LICENSE
